kails/__init__.py
kails/kails.py
kails-0.1.dist-info/LICENSE
kails-0.1.dist-info/METADATA
kails-0.1.dist-info/WHEEL
kails-0.1.dist-info/entry_points.txt
kails-0.1.dist-info/top_level.txt
kails-0.1.dist-info/RECORD
