Metadata-Version: 2.1
Name: kails
Version: 0.1
Summary: a cli for pywebview
Home-page: https://github.com/hxoreyer/kails
Author: hxoreyer
Author-email: 17396909632@163.com
Classifier: Programming Language :: Python :: 3
Classifier: License :: OSI Approved :: MIT License
Classifier: Operating System :: OS Independent
Requires-Python: >=3.6
License-File: LICENSE
Requires-Dist: watchdog
Requires-Dist: pywebview
